delphix/__init__.py
delphix/api/__init__.py
delphix/api/gateway/__init__.py
delphix/api/gateway/api_client.py
delphix/api/gateway/configuration.py
delphix/api/gateway/exceptions.py
delphix/api/gateway/model_utils.py
delphix/api/gateway/rest.py
delphix/api/gateway/api/__init__.py
delphix/api/gateway/api/api_clients_api.py
delphix/api/gateway/api/bookmarks_api.py
delphix/api/gateway/api/d_sources_api.py
delphix/api/gateway/api/engines_api.py
delphix/api/gateway/api/environments_api.py
delphix/api/gateway/api/jobs_api.py
delphix/api/gateway/api/management_api.py
delphix/api/gateway/api/snapshots_api.py
delphix/api/gateway/api/sources_api.py
delphix/api/gateway/api/vdbs_api.py
delphix/api/gateway/apis/__init__.py
delphix/api/gateway/model/__init__.py
delphix/api/gateway/model/api_client.py
delphix/api/gateway/model/api_client_create_parameter.py
delphix/api/gateway/model/api_client_create_response.py
delphix/api/gateway/model/base_provision_vdb_parameters.py
delphix/api/gateway/model/bookmark.py
delphix/api/gateway/model/create_bookmark_response.py
delphix/api/gateway/model/d_source.py
delphix/api/gateway/model/data_point_by_snapshot_parameters.py
delphix/api/gateway/model/data_point_by_timestamp_parameters.py
delphix/api/gateway/model/delete_vdb_parameters.py
delphix/api/gateway/model/delete_vdb_response.py
delphix/api/gateway/model/disable_vdb_parameters.py
delphix/api/gateway/model/disable_vdb_response.py
delphix/api/gateway/model/enable_vdb_parameters.py
delphix/api/gateway/model/enable_vdb_response.py
delphix/api/gateway/model/engine.py
delphix/api/gateway/model/engine_registration_parameter.py
delphix/api/gateway/model/engine_user_mapping.py
delphix/api/gateway/model/environment.py
delphix/api/gateway/model/error.py
delphix/api/gateway/model/errors.py
delphix/api/gateway/model/hashicorp_vault.py
delphix/api/gateway/model/hook.py
delphix/api/gateway/model/host.py
delphix/api/gateway/model/job.py
delphix/api/gateway/model/job_id.py
delphix_api_gateway-1.0.6.dist-info/METADATA
delphix_api_gateway-1.0.6.dist-info/WHEEL
delphix_api_gateway-1.0.6.dist-info/top_level.txt
delphix_api_gateway-1.0.6.dist-info/RECORD
